market_place_cli/__init__.py
market_place_cli/main_logic.py
market_place_cli/setup.py
market_place_cli/use_main_interface.py
market_place_cli/service_interface_logic/__init__.py
market_place_cli/service_interface_logic/cart_service_logic.py
market_place_cli/service_interface_logic/common.py
market_place_cli/service_interface_logic/initialization_logic.py
market_place_cli/service_interface_logic/market_service_logic.py
market_place_cli/service_interface_logic/order_service_logic.py
market_place_cli/service_interface_logic/user_service_logic.py
market_place_cli/service_interface_logic/version_service_logic.py
market_place_cli/service_interface_logic/wallet_service_logic.py
market_place_cli/service_interface_request/__init__.py
market_place_cli/service_interface_request/common_request.py
market_place_cli/service_interface_request/market_service_request.py
market_place_cli/service_interface_request/order_service_request.py
market_place_cli/service_interface_request/user_service_request.py
market_place_cli/service_interface_request/wallet_service_request.py
market_place_cli/utils/__init__.py
market_place_cli/utils/regex.py
market_place_cli/utils/string_utils.py
market_place_cli/v_cloud_market_cli_common/__init__.py
market_place_cli/v_cloud_market_cli_common/setup.py
market_place_cli/v_cloud_market_cli_common/config/__init__.py
market_place_cli/v_cloud_market_cli_common/config/server_config.py
market_place_cli/v_cloud_market_cli_common/config/wallet_config.py
market_place_cli/v_cloud_market_cli_common/service/__init__.py
market_place_cli/v_cloud_market_cli_common/service/cart_service.py
market_place_cli/v_cloud_market_cli_common/service/market_service.py
market_place_cli/v_cloud_market_cli_common/service/order_service.py
market_place_cli/v_cloud_market_cli_common/service/service_common.py
market_place_cli/v_cloud_market_cli_common/service/user_service.py
market_place_cli/v_cloud_market_cli_common/service/version_service.py
v_cloud_market_cli_user-0.10.1.dist-info/LICENSE
v_cloud_market_cli_user-0.10.1.dist-info/METADATA
v_cloud_market_cli_user-0.10.1.dist-info/WHEEL
v_cloud_market_cli_user-0.10.1.dist-info/entry_points.txt
v_cloud_market_cli_user-0.10.1.dist-info/top_level.txt
v_cloud_market_cli_user-0.10.1.dist-info/RECORD
